LICENSE
MANIFEST.in
README.md
pyproject.toml
setup.py
libero/__init__.py
libero.egg-info/PKG-INFO
libero.egg-info/SOURCES.txt
libero.egg-info/dependency_links.txt
libero.egg-info/requires.txt
libero.egg-info/top_level.txt
libero/configs/__init__.py
libero/libero/__init__.py
libero/libero/bddl_files/libero_10/KITCHEN_SCENE3_turn_on_the_stove_and_put_the_moka_pot_on_it.bddl
libero/libero/bddl_files/libero_10/KITCHEN_SCENE4_put_the_black_bowl_in_the_bottom_drawer_of_the_cabinet_and_close_it.bddl
libero/libero/bddl_files/libero_10/KITCHEN_SCENE6_put_the_yellow_and_white_mug_in_the_microwave_and_close_it.bddl
libero/libero/bddl_files/libero_10/KITCHEN_SCENE8_put_both_moka_pots_on_the_stove.bddl
libero/libero/bddl_files/libero_10/LIVING_ROOM_SCENE1_put_both_the_alphabet_soup_and_the_cream_cheese_box_in_the_basket.bddl
libero/libero/bddl_files/libero_10/LIVING_ROOM_SCENE2_put_both_the_alphabet_soup_and_the_tomato_sauce_in_the_basket.bddl
libero/libero/bddl_files/libero_10/LIVING_ROOM_SCENE2_put_both_the_cream_cheese_box_and_the_butter_in_the_basket.bddl
libero/libero/bddl_files/libero_10/LIVING_ROOM_SCENE5_put_the_white_mug_on_the_left_plate_and_put_the_yellow_and_white_mug_on_the_right_plate.bddl
libero/libero/bddl_files/libero_10/LIVING_ROOM_SCENE6_put_the_white_mug_on_the_plate_and_put_the_chocolate_pudding_to_the_right_of_the_plate.bddl
libero/libero/bddl_files/libero_10/STUDY_SCENE1_pick_up_the_book_and_place_it_in_the_back_compartment_of_the_caddy.bddl
libero/libero/bddl_files/libero_10/tasks_info.txt
libero/libero/bddl_files/libero_90/KITCHEN_SCENE10_close_the_top_drawer_of_the_cabinet.bddl
libero/libero/bddl_files/libero_90/KITCHEN_SCENE10_close_the_top_drawer_of_the_cabinet_and_put_the_black_bowl_on_top_of_it.bddl
libero/libero/bddl_files/libero_90/KITCHEN_SCENE10_put_the_black_bowl_in_the_top_drawer_of_the_cabinet.bddl
libero/libero/bddl_files/libero_90/KITCHEN_SCENE10_put_the_butter_at_the_back_in_the_top_drawer_of_the_cabinet_and_close_it.bddl
libero/libero/bddl_files/libero_90/KITCHEN_SCENE10_put_the_butter_at_the_front_in_the_top_drawer_of_the_cabinet_and_close_it.bddl
